docs/source/conf.py
optimask/__init__.py
optimask/_misc.py
optimask/_optimask.py
optimask/utils/__init__.py
optimask/utils/_plot.py
optimask/utils/_random_nan.py
optimask-1.3.11.dist-info/licenses/LICENSE
tests/test_optimask.py
optimask-1.3.11.dist-info/METADATA
optimask-1.3.11.dist-info/WHEEL
optimask-1.3.11.dist-info/top_level.txt
optimask-1.3.11.dist-info/RECORD
