Metadata-Version: 2.4
Name: optimask
Version: 1.3.11
Summary: OptiMask: extracting the largest (non-contiguous) submatrix without NaN
Author: Cyril Joly
License: MIT
Project-URL: documentation, https://optimask.readthedocs.io
Classifier: License :: OSI Approved :: MIT License
License-File: LICENSE
Requires-Dist: numpy
Requires-Dist: pandas
Requires-Dist: numba
Dynamic: license-file
